ds_util/__init__.py
ds_util/anonymize.py
ds_util/bloomfilter.py
ds_util/util.py
tests/__init__.py
tests/anonymization_test.py
phd_dataset_util-0.2.7.dist-info/LICENSE
phd_dataset_util-0.2.7.dist-info/METADATA
phd_dataset_util-0.2.7.dist-info/WHEEL
phd_dataset_util-0.2.7.dist-info/top_level.txt
phd_dataset_util-0.2.7.dist-info/RECORD
