Metadata-Version: 2.1
Name: phd-dataset-util
Version: 0.2.7
Summary: A package that aims to execute the basic data processing from my phd experiments
Home-page: https://github.com/thiaonobrega/ml_ds_util
Author: Thiago Nóbrega
Author-email: thiagonobrega@gmail.com
License: UNKNOWN
Platform: UNKNOWN
Classifier: Programming Language :: Python :: 3
Classifier: License :: OSI Approved :: GNU General Public License v3 (GPLv3)
Classifier: Operating System :: OS Independent
License-File: LICENSE
